ipython_openai/__init__.py
ipython_openai/gpt.py
ipython_openai-0.0.5.dist-info/LICENSE
ipython_openai-0.0.5.dist-info/METADATA
ipython_openai-0.0.5.dist-info/WHEEL
ipython_openai-0.0.5.dist-info/entry_points.txt
ipython_openai-0.0.5.dist-info/top_level.txt
ipython_openai-0.0.5.dist-info/RECORD
