Metadata-Version: 2.1
Name: ipython-openai
Version: 0.0.5
Summary: An IPython extension for interacting with OpenAI's models
Home-page: https://github.com/dustmason/ipython_openai
Author: Jordan Sitkin
Author-email: jordan@fiftyfootfoghorn.com
License: UNKNOWN
Platform: UNKNOWN
Classifier: Programming Language :: Python :: 3
Classifier: License :: OSI Approved :: MIT License
Classifier: Operating System :: OS Independent
Classifier: Framework :: IPython
Requires-Python: >=3.6
License-File: LICENSE
Requires-Dist: openai
Requires-Dist: ipython >=7.0
Requires-Dist: prompt-toolkit >=2.0.0
Requires-Dist: pygments
